{
  "data": [
    {
      "mode": "lines+markers",
      "type": "scatter",
      "x": null,
      "xaxis": "x",
      "y": null,
      "yaxis": "y"
    },
    {
      "mode": "lines+markers",
      "type": "scatter",
      "x": null,
      "xaxis": "x2",
      "y": null,
      "yaxis": "y2"
    }
  ],
  "layout": {
    "shapes": [
      {
        "line": {
          "dash": "dot"
        },
        "name": null,
        "type": "line",
        "x0": 0,
        "x1": 1,
        "xref": "x domain",
        "y0": null,
        "y1": null,
        "yref": "y"
      },
      {
        "name": null,
        "type": "line",
        "x0": 0,
        "x1": 1,
        "xref": "x domain",
        "y0": null,
        "y1": null,
        "yref": "y"
      },
      {
        "name": null,
        "type": "line",
        "x0": 0,
        "x1": 1,
        "xref": "x domain",
        "y0": null,
        "y1": null,
        "yref": "y"
      },
      {
        "line": {
          "dash": "dot"
        },
        "name": null,
        "type": "line",
        "x0": 0,
        "x1": 1,
        "xref": "x2 domain",
        "y0": null,
        "y1": null,
        "yref": "y2"
      },
      {
        "name": null,
        "type": "line",
        "x0": 0,
        "x1": 1,
        "xref": "x2 domain",
        "y0": null,
        "y1": null,
        "yref": "y2"
      },
      {
        "name": null,
        "type": "line",
        "x0": 0,
        "x1": 1,
        "xref": "x2 domain",
        "y0": null,
        "y1": null,
        "yref": "y2"
      }
    ],
    "showlegend": false,
    "xaxis": {
      "anchor": "y",
      "domain": [
        0,
        1
      ],
      "showgrid": false,
      "title": {
        "text": null
      },
      "zeroline": false
    },
    "xaxis2": {
      "anchor": "y2",
      "domain": [
        0,
        1
      ],
      "showgrid": false,
      "title": {
        "text": null
      },
      "zeroline": false
    },
    "yaxis": {
      "anchor": "x",
      "domain": [
        0.575,
        1
      ],
      "showgrid": false,
      "title": {
        "text": null
      },
      "zeroline": false
    },
    "yaxis2": {
      "anchor": "x2",
      "domain": [
        0,
        0.425
      ],
      "showgrid": false,
      "title": {
        "text": null
      },
      "zeroline": false
    }
  }
}